lockss/pyclient/__init__.py
lockss/pyclient/config/__init__.py
lockss/pyclient/config/api/__init__.py
lockss/pyclient/config/api/aus_api.py
lockss/pyclient/config/api/config_api.py
lockss/pyclient/config/api/plugins_api.py
lockss/pyclient/config/api/status_api.py
lockss/pyclient/config/api/tdb_api.py
lockss/pyclient/config/api/users_api.py
lockss/pyclient/config/api/utils_api.py
lockss/pyclient/config/api_client.py
lockss/pyclient/config/configuration.py
lockss/pyclient/config/models/__init__.py
lockss/pyclient/config/models/api_status.py
lockss/pyclient/config/models/au_configuration.py
lockss/pyclient/config/models/au_status.py
lockss/pyclient/config/models/au_ws_result.py
lockss/pyclient/config/models/auids_body.py
lockss/pyclient/config/models/check_substance_result.py
lockss/pyclient/config/models/content_configuration_result.py
lockss/pyclient/config/models/file_section_name_body.py
lockss/pyclient/config/models/platform_configuration_ws_result.py
lockss/pyclient/config/models/plugin_ws_result.py
lockss/pyclient/config/models/request_au_control_result.py
lockss/pyclient/config/models/tdb_au_ws_result.py
lockss/pyclient/config/models/tdb_publisher_ws_result.py
lockss/pyclient/config/models/tdb_title_ws_result.py
lockss/pyclient/config/rest.py
lockss/pyclient/crawler/__init__.py
lockss/pyclient/crawler/api/__init__.py
lockss/pyclient/crawler/api/crawlers_api.py
lockss/pyclient/crawler/api/crawls_api.py
lockss/pyclient/crawler/api/jobs_api.py
lockss/pyclient/crawler/api/status_api.py
lockss/pyclient/crawler/api/ws_api.py
lockss/pyclient/crawler/api_client.py
lockss/pyclient/crawler/configuration.py
lockss/pyclient/crawler/models/__init__.py
lockss/pyclient/crawler/models/api_status.py
lockss/pyclient/crawler/models/counter.py
lockss/pyclient/crawler/models/crawl_desc.py
lockss/pyclient/crawler/models/crawl_job.py
lockss/pyclient/crawler/models/crawl_pager.py
lockss/pyclient/crawler/models/crawl_status.py
lockss/pyclient/crawler/models/crawl_ws_result.py
lockss_pyclient-0.1.0.dev2.dist-info/LICENSE
lockss_pyclient-0.1.0.dev2.dist-info/METADATA
lockss_pyclient-0.1.0.dev2.dist-info/WHEEL
lockss_pyclient-0.1.0.dev2.dist-info/RECORD
